MANIFEST.in
README.md
setup.py
django_sendmail_backend/__init__.py
django_sendmail_backend/backends.py
django_sendmail_backend.egg-info/PKG-INFO
django_sendmail_backend.egg-info/SOURCES.txt
django_sendmail_backend.egg-info/dependency_links.txt
django_sendmail_backend.egg-info/requires.txt
django_sendmail_backend.egg-info/top_level.txt