Metadata-Version: 1.1
Name: django-sendmail-backend
Version: 0.1.2
Summary: Its a simple command line sendmail backend for Django
Home-page: https://github.com/perenecabuto/django-sendmail-backend.git
Author: Felipe Ramos
Author-email: perenecabuto@gmail.com
License: BSD
Keywords: Django,Python,sendmail,EMAIL_BACKEND,command line,mta
Platform: UNKNOWN
Classifier: Development Status :: 4 - Beta
Classifier: Environment :: Web Environment
Classifier: Intended Audience :: Developers
Classifier: License :: OSI Approved :: BSD License
Classifier: Operating System :: OS Independent
Classifier: Programming Language :: Python
Classifier: Framework :: Django
